tax_module/__init__.py
tax_module/errors.py
tax_module/gst.py
tax_module/indian_tax.py
tax_module/models.py
tax_module/tds.py
tests/__init__.py
tests/factories.py
tests/test_gst_module.py
tests/test_tds_module.py
tax_module-0.0.5.dist-info/METADATA
tax_module-0.0.5.dist-info/WHEEL
tax_module-0.0.5.dist-info/top_level.txt
tax_module-0.0.5.dist-info/RECORD
