Metadata-Version: 2.1
Name: tax-module
Version: 0.0.5
Summary: Tax module
Home-page: https://github.com/Shuttl-Tech/tax-module.git
Author: Shuttl
Author-email: sherub.thakur@shuttl.com
License: MIT
Platform: UNKNOWN
Classifier: Programming Language :: Python :: 3.7
Requires-Dist: pytz
Requires-Dist: voluptuous
Requires-Dist: pyshuttlis
Provides-Extra: dev
Requires-Dist: flake8 ; extra == 'dev'
Provides-Extra: test
Requires-Dist: pytest ; extra == 'test'
Requires-Dist: pytest-runner ; extra == 'test'
Requires-Dist: pytest-cov ; extra == 'test'
Requires-Dist: pytest-pep8 ; extra == 'test'
